iconipy/__init__.py
iconipy/__pyinstaller.py
iconipy/iconipy.py
iconipy/assets/boxicons/LICENSE.txt
iconipy/assets/boxicons/boxicons.css
iconipy/assets/boxicons/boxicons.ttf
iconipy/assets/boxicons/version.txt
iconipy/assets/ligature_symbols/LICENSE.txt
iconipy/assets/ligature_symbols/LigatureSymbols-2.11.ttf
iconipy/assets/ligature_symbols/index.html
iconipy/assets/ligature_symbols/version.txt
iconipy/assets/lineicons/LICENSE.md
iconipy/assets/lineicons/lineicons.ttf
iconipy/assets/lineicons/unicodesMap.json
iconipy/assets/lineicons/version.txt
iconipy/assets/lucide/LICENSE.txt
iconipy/assets/lucide/info.json
iconipy/assets/lucide/lucide.ttf
iconipy/assets/lucide/version.txt
iconipy/assets/material_icons_outlined_regular/LICENSE.txt
iconipy/assets/material_icons_outlined_regular/MaterialIconsOutlined-Regular.codepoints
iconipy/assets/material_icons_outlined_regular/MaterialIconsOutlined-Regular.otf
iconipy/assets/material_icons_outlined_regular/version.txt
iconipy/assets/material_icons_regular/LICENSE.txt
iconipy/assets/material_icons_regular/MaterialIcons-Regular.codepoints
iconipy/assets/material_icons_regular/MaterialIcons-Regular.ttf
iconipy/assets/material_icons_regular/version.txt
iconipy/assets/material_icons_round_regular/LICENSE.txt
iconipy/assets/material_icons_round_regular/MaterialIconsRound-Regular.codepoints
iconipy/assets/material_icons_round_regular/MaterialIconsRound-Regular.otf
iconipy/assets/material_icons_round_regular/version.txt
iconipy/assets/material_icons_sharp_regular/LICENSE.txt
iconipy/assets/material_icons_sharp_regular/MaterialIconsSharp-Regular.codepoints
iconipy/assets/material_icons_sharp_regular/MaterialIconsSharp-Regular.otf
iconipy/assets/material_icons_sharp_regular/version.txt
iconipy/assets/microns/LICENCE.md
iconipy/assets/microns/microns.css
iconipy/assets/microns/microns.ttf
iconipy/assets/microns/version.txt
iconipy/assets/typicons/LICENCE.md
iconipy/assets/typicons/typicons.css
iconipy/assets/typicons/typicons.ttf
iconipy-0.5.0.dist-info/licenses/LICENSE
iconipy-0.5.0.dist-info/METADATA
iconipy-0.5.0.dist-info/WHEEL
iconipy-0.5.0.dist-info/entry_points.txt
iconipy-0.5.0.dist-info/top_level.txt
iconipy-0.5.0.dist-info/RECORD
