Metadata-Version: 2.4
Name: iconipy
Version: 0.5.0
Summary: Create icons for user interfaces directly from your Python code.
Home-page: https://github.com/digidigital/iconipy
Author: Björn Seipel
Author-email: Björn Seipel <support@digidigital.de>
Project-URL: Homepage, https://github.com/digidigital/iconipy
Project-URL: Documentation, https://iconipy.digidigital.de
Project-URL: Issues, https://github.com/digidigital/iconipy/issues
Project-URL: SampleCode, https://github.com/digidigital/iconipy/tree/main/demo_programs
Keywords: UI,GUI,icons,image,icon
Classifier: Development Status :: 5 - Production/Stable
Classifier: Programming Language :: Python :: 3
Classifier: License :: OSI Approved :: MIT License
Classifier: Operating System :: OS Independent
Classifier: Intended Audience :: Developers
Requires-Python: >=3.8
License-File: LICENSE
Requires-Dist: pillow>=10.0.0
Dynamic: author
Dynamic: home-page
Dynamic: license-file
Dynamic: requires-python
